bonini2025/__init__.py
bonini2025/info.py
bonini2025/version.py
bonini2025/clean/fig1.csv
bonini2025/clean/fig2.csv
bonini2025/clean/fig3.csv
bonini2025/clean/fig4.csv
bonini2025/clean/info.json
bonini2025/clean/readme.rst
bonini2025/clean/tab2.csv
bonini2025/clean/tab4.csv
bonini2025/clean/tab5.csv
bonini2025-0.1.1.dist-info/licenses/AUTHORS.rst
bonini2025-0.1.1.dist-info/licenses/LICENSE
bonini2025-0.1.1.dist-info/METADATA
bonini2025-0.1.1.dist-info/WHEEL
bonini2025-0.1.1.dist-info/top_level.txt
bonini2025-0.1.1.dist-info/RECORD
