Metadata-Version: 2.4
Name: bonini2025
Version: 0.1.1
Summary: Data and formalisms from Bonini et al. (2025)
Author-email: revesansparole <revesansparole@gmail.com>
Maintainer-email: revesansparole <revesansparole@gmail.com>, Jerome Chopard <revesansparole@gmail.com>
License: cc_by_nc
Project-URL: repository, https://gitlab.com/b326/bonini2025
Project-URL: pip, https://pypi.org/project/bonini2025/0.1.1/
Project-URL: conda, https://anaconda.org/revesansparole/bonini2025
Project-URL: doc, https://b326.gitlab.io/bonini2025/
Project-URL: pypi, https://badge.fury.io/py/bonini2025
Classifier: Development Status :: 2 - Pre-Alpha
Classifier: Intended Audience :: Developers
Classifier: License :: OSI Approved :: BSD License
Classifier: Natural Language :: English
Classifier: Programming Language :: Python
Classifier: Programming Language :: Python :: 3
Classifier: Programming Language :: Python :: 3 :: Only
Classifier: Programming Language :: Python :: 3.10
Classifier: Programming Language :: Python :: 3.11
Classifier: Programming Language :: Python :: 3.12
Classifier: Programming Language :: Python :: 3.13
Requires-Python: >=3.10
License-File: LICENSE
License-File: AUTHORS.rst
Provides-Extra: doc
Requires-Dist: sphinx; extra == "doc"
Requires-Dist: sphinx-gallery; extra == "doc"
Requires-Dist: sphinx-rtd-theme; extra == "doc"
Provides-Extra: dvlpt
Requires-Dist: black; extra == "dvlpt"
Requires-Dist: twine; extra == "dvlpt"
Provides-Extra: example
Requires-Dist: matplotlib; extra == "example"
Requires-Dist: pandas; extra == "example"
Provides-Extra: script
Requires-Dist: graphextract; extra == "script"
Requires-Dist: numpy; extra == "script"
Requires-Dist: pandas; extra == "script"
Provides-Extra: test
Requires-Dist: coverage; extra == "test"
Requires-Dist: pandas; extra == "test"
Requires-Dist: pytest; extra == "test"
Requires-Dist: pytest-cov; extra == "test"
Requires-Dist: pytest-mock; extra == "test"
Dynamic: license-file
